okin/base/__init__.py
okin/base/atom.py
okin/base/chem_logger.py
okin/base/chem_plot_utils.py
okin/base/compound.py
okin/base/reaction.py
okin/cd_parser/__init__.py
okin/cd_parser/cd_parser.py
okin/cd_parser/CDClasses/__init__.py
okin/cd_parser/CDClasses/cd_arrow.py
okin/cd_parser/CDClasses/cd_chem.py
okin/cd_parser/CDClasses/cd_fragment.py
okin/cd_parser/CDClasses/cd_line.py
okin/cd_parser/CDClasses/cd_reaction.py
okin/cd_parser/CDClasses/cd_text.py
okin/kinetics/__init__.py
okin/kinetics/cc_solver.py
okin/kinetics/tfs.py
okin/kinetics/vtna.py
okin/model/__init__.py
okin/model/augmentor.py
okin/model/modler.py
okin/simulation/__init__.py
okin/simulation/rate_equation.py
okin/simulation/simulator.py
okin/simulation/tc_engine.py
okin/simulation/tcc.py
okin/simulation/examples/base_chem_test.py
okin/simulation/examples/chemdraw_test.py
okin/simulation/examples/rate_equation_test.py
okin/simulation/examples/simultion_test.py
okin/simulation/examples/test_all.py
okin-0.1.4.dist-info/licenses/LICENSE
okin-0.1.4.dist-info/METADATA
okin-0.1.4.dist-info/WHEEL
okin-0.1.4.dist-info/top_level.txt
okin-0.1.4.dist-info/RECORD
