Metadata-Version: 2.4
Name: okin
Version: 0.1.4
Summary: Organic-Kinetics (okin) is a collection of chemistry-related Python tools
Author: Finn Bork, Dylan Pyle
Project-URL: Source, https://github.com/Kaffejunge/okin
Requires-Python: >=3.9
License-File: LICENSE
Requires-Dist: matplotlib
Requires-Dist: mendeleev
Requires-Dist: scipy
Requires-Dist: pandas
Requires-Dist: scikit-learn
Requires-Dist: sympy
Requires-Dist: tellurium
Requires-Dist: numpy==1.26.4
Dynamic: license-file
